systemd_watchdog_thread/__init__.py
systemd_watchdog_thread/watchdogthread.py
systemd_watchdog_thread-1.1.dist-info/LICENSE
systemd_watchdog_thread-1.1.dist-info/METADATA
systemd_watchdog_thread-1.1.dist-info/WHEEL
systemd_watchdog_thread-1.1.dist-info/top_level.txt
systemd_watchdog_thread-1.1.dist-info/RECORD
