Metadata-Version: 2.1
Name: systemd-watchdog-thread
Version: 1.1
Author: Gerard
Author-email: gweatherby@uchc.edu
License: MIT License
Project-URL: Homepage, https://github.com/NMRhub/systemd-watchdog-thread
Project-URL: Issues, https://github.com/NMRhub/systemd-watchdog-thread/issues
Classifier: Programming Language :: Python :: 3
Classifier: License :: OSI Approved :: MIT License
Classifier: Operating System :: POSIX :: Linux
Requires-Python: >=3.8
License-File: LICENSE
Requires-Dist: sdnotify
